tnode/__init__.py
tnode/__meta__.py
tnode/file_utils.py
tnode/interface.py
tnode/parent_child.py
tnode/__pycache__/__init__.cpython-36.pyc
tnode/__pycache__/__init__.cpython-38.pyc
tnode/__pycache__/__meta__.cpython-36.pyc
tnode/__pycache__/__meta__.cpython-38.pyc
tnode/__pycache__/file_utils.cpython-36.pyc
tnode/__pycache__/file_utils.cpython-38.pyc
tnode/__pycache__/interface.cpython-36.pyc
tnode/__pycache__/interface.cpython-38.pyc
tnode/__pycache__/parent_child.cpython-36.pyc
tnode/__pycache__/parent_child.cpython-38.pyc
tnode-1.1.1.dist-info/LICENSE
tnode-1.1.1.dist-info/METADATA
tnode-1.1.1.dist-info/WHEEL
tnode-1.1.1.dist-info/top_level.txt
tnode-1.1.1.dist-info/RECORD
