Metadata-Version: 2.1
Name: tnode
Version: 1.1.1
Summary: Tree node list utilities
Home-page: https://github.com/justengel/tnode
Author: Justin Engel
Author-email: jtengel08@gmail.com
License: MIT
Download-URL: https://github.com/justengel/tnode/archive/v1.1.1.tar.gz
Keywords: TNode Tree Node
Platform: any
Classifier: Programming Language :: Python
Classifier: Programming Language :: Python :: 3
Classifier: Operating System :: OS Independent
License-File: LICENSE
Requires-Dist: dynamicmethod (>=1.1.0)
